Workbook

Sheet 1. Read Me
A1: Q3 COCKPIT — IGNIS & CLEANCOOKIQ
A2: One file for the whole quarter (Jul–Sep 2026) · Guided by four north stars
A4: THE FOUR NORTH STARS (they guide every week)
A5: Programmes | B5: What the money builds & delivers — Prisons, CCIQ launch, Uganda, Sierra Leone, household pilot, DMRV.
A6: Partnerships | B6: The six strategic relationships — FSD, Rockefeller, GEAPP, KCB, Caritas, AfDB (+ anchor funder).
A7: Revenue | B7: All money in. $100,000 is the floor, not the ceiling.
A8: Team | B8: Ownership, cadence, systems & compliance — everyone runs their own workstream.
A10: HOW THIS COCKPIT WORKS (all 13 weeks live in this one file)
A11: Before the meeting | B11: Everyone sends Joan their five lines. Joan sets each north star's RAG and fills the next week block on the Run-Sheet.
A12: At the meeting | B12: Read the four north stars first (are we green/amber/red on Programmes, Partnerships, Revenue, Team?), then each person's line.
A13: To close | B13: Every red item moves to the Decision Log with an owner and a next action.
A14: Across the quarter | B14: Never start a new document — move to the next week block. The Cockpit home shows the whole-quarter trajectory automatically.
A16: THE RULES OF THE ROOM
A17: • North stars first — data before narrative.
A18: • Named blockers only. No status reports.
A19: • MD speaks last.
A20: • Every red item gets a next action + named owner before we close.
A21: • Pipeline lives here — 1:1s are for career, blockers and quality of thinking.
A23: THE FIVE LINES (send to Joan ahead of the meeting)
A24: Elizabeth & Wilson (pipeline) | C24: 1. Revenue & pipeline: this week vs last | 2. Deals / partnerships advanced | 3. Any deal stalled >14 days — name it + blocker | 4. One win | 5. One ask from Dennis
A25: Brian (technology) | C25: 1. Features shipped | 2. Features blocked + why | 3. Uptime & incidents | 4. Three delivery commitments next week | 5. One ask from Dennis or Joan
A26: Dennis | C26: Brings the 5 CEO dashboard numbers (shared every Monday). Speaks last.
A27: Joan | C27: Compiles the RAG, fills the week block, maintains the Decision Log.
A29: RAG KEY
A30: Green | B30: On track
A34: Amber | B34: At risk — watch / needs input
A38: Red | B38: Off track — decision needed
A42: Done | B42: Delivered
A46: Not Started | B46: Not yet begun

Sheet 2. Q3 Cockpit
A1: Q3 COCKPIT — HOME
A2: Four north stars · revenue to $100K · whole-quarter trajectory (auto from Run-Sheet)
A4: NORTH-STAR STATUS (Joan's weekly synthesis)
A5: North Star | D5: RAG | E5: Where it stands this week
A6: Programmes | D6: Amber | E6: wk 8/13 RAG UNSET (2 of 5 reported). 26 Aug Voi convening restructured to one integrated full day with a Financing Forum; Tectona fieldwork rerouted while the Mui MoU stays delayed; DMRV contracting at risk after the 4R Digital deferral. Last scored RAG is week 7.
A7: Partnerships | D7: Green | E7: wk 8/13 RAG UNSET. The deciding fact is missing: the FSD MoU signature targeted 17 to 18 Aug was not confirmed by anyone. Elsewhere CESA is at 14 pages with one open item, the IRENA sub agreement is cleared to execute, Zambia/CES priorities are agreed for a 3 Sep call. Last scored RAG is week 7.
A8: Revenue | D8: Amber | E8: wk 8/13 RAG UNSET. No new revenue closed, position holds at $11K signed of the $100K floor at week 8 of 13. Restated FY26 financials received 20 Aug, so burn and runway can now be stated. Last scored RAG is week 7.
A9: Team | D9: Green | E9: wk 8/13 RAG UNSET. Reporting fell to 2 of 5 with three unexcused misses including the MD, the worst week of the quarter. Output from the two reporters was strong: CESA 27 to 14 pages, FY26 financial review owned, withholding tax filed. Last scored RAG is week 7.
A11: REVENUE TO $100,000 FLOOR (fill 'Signed $' as money lands · $100K is the floor, not the ceiling)
A12: Deal / source | H12: Target $ | J12: Signed $ | L12: Owner | N12: Note
A13: Prisons | H13: 70000 | L13: Wilson | N13: $70k–100k range
A14: Rockefeller | H14: 150000 | L14: Elizabeth
A15: CLASP | H15: 10000 | L15: Elizabeth
A16: UNDP | L16: Elizabeth | N16: TBD — confirm amount
A17: IRENA + CCAK | H17: 15000 | J17: 8000 | L17: Dennis | N17: SIGNED (countersigned Aug 3) — confirmed contract value $8,000 (revised down from $15,000 estimate)
A18: Uganda | H18: 20000 | L18: Dennis
A19: Sierra Leone (20 schools licensed) | L19: Dennis | N19: TBD — confirm amount
A20: Energy consultancy (short-term) | J20: 3000 | L20: Dennis | N20: New signed engagement, short term energy consultancy (Dennis). No new revenue closed in W8.
A21: TOTALS · identified vs signed (floor $100,000) | H21: =SUM(H13:H20) -> 265000 | J21: =SUM(J13:J20) -> 11000 | L21: =IF(SUM(J13:J20)=0,"signed $0 of $100k floor","signed = "&TEXT(SUM(J13:J20)/100000,"0%")&" of floor") -> signed = 11% of floor
A23: NORTH-STAR TRAJECTORY — 13 WEEKS (auto from Run-Sheet)
A24: North Star | B24: W1 | C24: W2 | D24: W3 | E24: W4 | F24: W5 | G24: W6 | H24: W7 | I24: W8 | J24: W9 | K24: W10 | L24: W11 | M24: W12 | N24: W13
A25: Programmes | B25: =IF('3. Weekly Run-Sheet'!B6="","",'3. Weekly Run-Sheet'!B6) | C25: =IF('3. Weekly Run-Sheet'!B20="","",'3. Weekly Run-Sheet'!B20) -> Amber | D25: =IF('3. Weekly Run-Sheet'!B34="","",'3. Weekly Run-Sheet'!B34) -> Amber | E25: =IF('3. Weekly Run-Sheet'!B48="","",'3. Weekly Run-Sheet'!B48) -> Amber | F25: =IF('3. Weekly Run-Sheet'!B62="","",'3. Weekly Run-Sheet'!B62) -> Amber | G25: =IF('3. Weekly Run-Sheet'!B76="","",'3. Weekly Run-Sheet'!B76) -> Amber | H25: =IF('3. Weekly Run-Sheet'!B90="","",'3. Weekly Run-Sheet'!B90) -> Amber | I25: =IF('3. Weekly Run-Sheet'!B104="","",'3. Weekly Run-Sheet'!B104) | J25: =IF('3. Weekly Run-Sheet'!B118="","",'3. Weekly Run-Sheet'!B118) | K25: =IF('3. Weekly Run-Sheet'!B132="","",'3. Weekly Run-Sheet'!B132) | L25: =IF('3. Weekly Run-Sheet'!B146="","",'3. Weekly Run-Sheet'!B146) | M25: =IF('3. Weekly Run-Sheet'!B160="","",'3. Weekly Run-Sheet'!B160) | N25: =IF('3. Weekly Run-Sheet'!B174="","",'3. Weekly Run-Sheet'!B174)
A26: Partnerships | B26: =IF('3. Weekly Run-Sheet'!B7="","",'3. Weekly Run-Sheet'!B7) | C26: =IF('3. Weekly Run-Sheet'!B21="","",'3. Weekly Run-Sheet'!B21) -> Amber | D26: =IF('3. Weekly Run-Sheet'!B35="","",'3. Weekly Run-Sheet'!B35) -> Amber | E26: =IF('3. Weekly Run-Sheet'!B49="","",'3. Weekly Run-Sheet'!B49) -> Green | F26: =IF('3. Weekly Run-Sheet'!B63="","",'3. Weekly Run-Sheet'!B63) -> Green | G26: =IF('3. Weekly Run-Sheet'!B77="","",'3. Weekly Run-Sheet'!B77) -> Green | H26: =IF('3. Weekly Run-Sheet'!B91="","",'3. Weekly Run-Sheet'!B91) -> Green | I26: =IF('3. Weekly Run-Sheet'!B105="","",'3. Weekly Run-Sheet'!B105) | J26: =IF('3. Weekly Run-Sheet'!B119="","",'3. Weekly Run-Sheet'!B119) | K26: =IF('3. Weekly Run-Sheet'!B133="","",'3. Weekly Run-Sheet'!B133) | L26: =IF('3. Weekly Run-Sheet'!B147="","",'3. Weekly Run-Sheet'!B147) | M26: =IF('3. Weekly Run-Sheet'!B161="","",'3. Weekly Run-Sheet'!B161) | N26: =IF('3. Weekly Run-Sheet'!B175="","",'3. Weekly Run-Sheet'!B175)
A27: Revenue | B27: =IF('3. Weekly Run-Sheet'!B8="","",'3. Weekly Run-Sheet'!B8) | C27: =IF('3. Weekly Run-Sheet'!B22="","",'3. Weekly Run-Sheet'!B22) -> Amber | D27: =IF('3. Weekly Run-Sheet'!B36="","",'3. Weekly Run-Sheet'!B36) -> Amber | E27: =IF('3. Weekly Run-Sheet'!B50="","",'3. Weekly Run-Sheet'!B50) -> Amber | F27: =IF('3. Weekly Run-Sheet'!B64="","",'3. Weekly Run-Sheet'!B64) -> Amber | G27: =IF('3. Weekly Run-Sheet'!B78="","",'3. Weekly Run-Sheet'!B78) -> Amber | H27: =IF('3. Weekly Run-Sheet'!B92="","",'3. Weekly Run-Sheet'!B92) -> Amber | I27: =IF('3. Weekly Run-Sheet'!B106="","",'3. Weekly Run-Sheet'!B106) | J27: =IF('3. Weekly Run-Sheet'!B120="","",'3. Weekly Run-Sheet'!B120) | K27: =IF('3. Weekly Run-Sheet'!B134="","",'3. Weekly Run-Sheet'!B134) | L27: =IF('3. Weekly Run-Sheet'!B148="","",'3. Weekly Run-Sheet'!B148) | M27: =IF('3. Weekly Run-Sheet'!B162="","",'3. Weekly Run-Sheet'!B162) | N27: =IF('3. Weekly Run-Sheet'!B176="","",'3. Weekly Run-Sheet'!B176)
A28: Team | B28: =IF('3. Weekly Run-Sheet'!B9="","",'3. Weekly Run-Sheet'!B9) | C28: =IF('3. Weekly Run-Sheet'!B23="","",'3. Weekly Run-Sheet'!B23) -> Amber | D28: =IF('3. Weekly Run-Sheet'!B37="","",'3. Weekly Run-Sheet'!B37) -> Amber | E28: =IF('3. Weekly Run-Sheet'!B51="","",'3. Weekly Run-Sheet'!B51) -> Amber | F28: =IF('3. Weekly Run-Sheet'!B65="","",'3. Weekly Run-Sheet'!B65) -> Green | G28: =IF('3. Weekly Run-Sheet'!B79="","",'3. Weekly Run-Sheet'!B79) -> Green | H28: =IF('3. Weekly Run-Sheet'!B93="","",'3. Weekly Run-Sheet'!B93) -> Green | I28: =IF('3. Weekly Run-Sheet'!B107="","",'3. Weekly Run-Sheet'!B107) | J28: =IF('3. Weekly Run-Sheet'!B121="","",'3. Weekly Run-Sheet'!B121) | K28: =IF('3. Weekly Run-Sheet'!B135="","",'3. Weekly Run-Sheet'!B135) | L28: =IF('3. Weekly Run-Sheet'!B149="","",'3. Weekly Run-Sheet'!B149) | M28: =IF('3. Weekly Run-Sheet'!B163="","",'3. Weekly Run-Sheet'!B163) | N28: =IF('3. Weekly Run-Sheet'!B177="","",'3. Weekly Run-Sheet'!B177)
A30: TEAM TRAJECTORY — 13 WEEKS (auto from Run-Sheet)
A31: Person | B31: W1 | C31: W2 | D31: W3 | E31: W4 | F31: W5 | G31: W6 | H31: W7 | I31: W8 | J31: W9 | K31: W10 | L31: W11 | M31: W12 | N31: W13
A32: Dennis | B32: =IF('3. Weekly Run-Sheet'!E11="","",'3. Weekly Run-Sheet'!E11) | C32: =IF('3. Weekly Run-Sheet'!E25="","",'3. Weekly Run-Sheet'!E25) | D32: =IF('3. Weekly Run-Sheet'!E39="","",'3. Weekly Run-Sheet'!E39) -> Red | E32: =IF('3. Weekly Run-Sheet'!E53="","",'3. Weekly Run-Sheet'!E53) -> Green | F32: =IF('3. Weekly Run-Sheet'!E67="","",'3. Weekly Run-Sheet'!E67) | G32: =IF('3. Weekly Run-Sheet'!E81="","",'3. Weekly Run-Sheet'!E81) -> Green | H32: =IF('3. Weekly Run-Sheet'!E95="","",'3. Weekly Run-Sheet'!E95) -> Green | I32: =IF('3. Weekly Run-Sheet'!E109="","",'3. Weekly Run-Sheet'!E109) -> Not Started | J32: =IF('3. Weekly Run-Sheet'!E123="","",'3. Weekly Run-Sheet'!E123) | K32: =IF('3. Weekly Run-Sheet'!E137="","",'3. Weekly Run-Sheet'!E137) | L32: =IF('3. Weekly Run-Sheet'!E151="","",'3. Weekly Run-Sheet'!E151) | M32: =IF('3. Weekly Run-Sheet'!E165="","",'3. Weekly Run-Sheet'!E165) | N32: =IF('3. Weekly Run-Sheet'!E179="","",'3. Weekly Run-Sheet'!E179)
A33: Elizabeth | B33: =IF('3. Weekly Run-Sheet'!E12="","",'3. Weekly Run-Sheet'!E12) | C33: =IF('3. Weekly Run-Sheet'!E26="","",'3. Weekly Run-Sheet'!E26) -> Amber | D33: =IF('3. Weekly Run-Sheet'!E40="","",'3. Weekly Run-Sheet'!E40) -> Green | E33: =IF('3. Weekly Run-Sheet'!E54="","",'3. Weekly Run-Sheet'!E54) -> Green | F33: =IF('3. Weekly Run-Sheet'!E68="","",'3. Weekly Run-Sheet'!E68) -> Green | G33: =IF('3. Weekly Run-Sheet'!E82="","",'3. Weekly Run-Sheet'!E82) -> Green | H33: =IF('3. Weekly Run-Sheet'!E96="","",'3. Weekly Run-Sheet'!E96) -> Not Started | I33: =IF('3. Weekly Run-Sheet'!E110="","",'3. Weekly Run-Sheet'!E110) -> Not Started | J33: =IF('3. Weekly Run-Sheet'!E124="","",'3. Weekly Run-Sheet'!E124) | K33: =IF('3. Weekly Run-Sheet'!E138="","",'3. Weekly Run-Sheet'!E138) | L33: =IF('3. Weekly Run-Sheet'!E152="","",'3. Weekly Run-Sheet'!E152) | M33: =IF('3. Weekly Run-Sheet'!E166="","",'3. Weekly Run-Sheet'!E166) | N33: =IF('3. Weekly Run-Sheet'!E180="","",'3. Weekly Run-Sheet'!E180)
A34: Wilson | B34: =IF('3. Weekly Run-Sheet'!E13="","",'3. Weekly Run-Sheet'!E13) | C34: =IF('3. Weekly Run-Sheet'!E27="","",'3. Weekly Run-Sheet'!E27) -> Amber | D34: =IF('3. Weekly Run-Sheet'!E41="","",'3. Weekly Run-Sheet'!E41) -> Amber | E34: =IF('3. Weekly Run-Sheet'!E55="","",'3. Weekly Run-Sheet'!E55) -> Green | F34: =IF('3. Weekly Run-Sheet'!E69="","",'3. Weekly Run-Sheet'!E69) -> Green | G34: =IF('3. Weekly Run-Sheet'!E83="","",'3. Weekly Run-Sheet'!E83) -> Green | H34: =IF('3. Weekly Run-Sheet'!E97="","",'3. Weekly Run-Sheet'!E97) -> Green | I34: =IF('3. Weekly Run-Sheet'!E111="","",'3. Weekly Run-Sheet'!E111) -> Green | J34: =IF('3. Weekly Run-Sheet'!E125="","",'3. Weekly Run-Sheet'!E125) | K34: =IF('3. Weekly Run-Sheet'!E139="","",'3. Weekly Run-Sheet'!E139) | L34: =IF('3. Weekly Run-Sheet'!E153="","",'3. Weekly Run-Sheet'!E153) | M34: =IF('3. Weekly Run-Sheet'!E167="","",'3. Weekly Run-Sheet'!E167) | N34: =IF('3. Weekly Run-Sheet'!E181="","",'3. Weekly Run-Sheet'!E181)
A35: Joan | B35: =IF('3. Weekly Run-Sheet'!E14="","",'3. Weekly Run-Sheet'!E14) | C35: =IF('3. Weekly Run-Sheet'!E28="","",'3. Weekly Run-Sheet'!E28) -> Green | D35: =IF('3. Weekly Run-Sheet'!E42="","",'3. Weekly Run-Sheet'!E42) -> Green | E35: =IF('3. Weekly Run-Sheet'!E56="","",'3. Weekly Run-Sheet'!E56) -> Green | F35: =IF('3. Weekly Run-Sheet'!E70="","",'3. Weekly Run-Sheet'!E70) -> Green | G35: =IF('3. Weekly Run-Sheet'!E84="","",'3. Weekly Run-Sheet'!E84) -> Green | H35: =IF('3. Weekly Run-Sheet'!E98="","",'3. Weekly Run-Sheet'!E98) -> Green | I35: =IF('3. Weekly Run-Sheet'!E112="","",'3. Weekly Run-Sheet'!E112) -> Green | J35: =IF('3. Weekly Run-Sheet'!E126="","",'3. Weekly Run-Sheet'!E126) | K35: =IF('3. Weekly Run-Sheet'!E140="","",'3. Weekly Run-Sheet'!E140) | L35: =IF('3. Weekly Run-Sheet'!E154="","",'3. Weekly Run-Sheet'!E154) | M35: =IF('3. Weekly Run-Sheet'!E168="","",'3. Weekly Run-Sheet'!E168) | N35: =IF('3. Weekly Run-Sheet'!E182="","",'3. Weekly Run-Sheet'!E182)
A36: Brian | B36: =IF('3. Weekly Run-Sheet'!E15="","",'3. Weekly Run-Sheet'!E15) | C36: =IF('3. Weekly Run-Sheet'!E29="","",'3. Weekly Run-Sheet'!E29) -> Amber | D36: =IF('3. Weekly Run-Sheet'!E43="","",'3. Weekly Run-Sheet'!E43) -> Amber | E36: =IF('3. Weekly Run-Sheet'!E57="","",'3. Weekly Run-Sheet'!E57) -> Green | F36: =IF('3. Weekly Run-Sheet'!E71="","",'3. Weekly Run-Sheet'!E71) -> Green | G36: =IF('3. Weekly Run-Sheet'!E85="","",'3. Weekly Run-Sheet'!E85) -> Green | H36: =IF('3. Weekly Run-Sheet'!E99="","",'3. Weekly Run-Sheet'!E99) -> Green | I36: =IF('3. Weekly Run-Sheet'!E113="","",'3. Weekly Run-Sheet'!E113) -> Not Started | J36: =IF('3. Weekly Run-Sheet'!E127="","",'3. Weekly Run-Sheet'!E127) | K36: =IF('3. Weekly Run-Sheet'!E141="","",'3. Weekly Run-Sheet'!E141) | L36: =IF('3. Weekly Run-Sheet'!E155="","",'3. Weekly Run-Sheet'!E155) | M36: =IF('3. Weekly Run-Sheet'!E169="","",'3. Weekly Run-Sheet'!E169) | N36: =IF('3. Weekly Run-Sheet'!E183="","",'3. Weekly Run-Sheet'!E183)

Sheet 3. Weekly Run-Sheet
A1: WEEKLY RUN-SHEET — Q3 2026
A2: North stars up top, people below · fill the current week, scroll down as the quarter runs
A4: WEEK 1 · w/c 29 Jun
A5: North Star | B5: RAG | C5: Where it stands (one line) | E5: This week's decisive move | G5: Lead(s)
A6: Programmes | G6: Wilson · Brian · Elizabeth
A7: Partnerships | G7: Dennis · Wilson
A8: Revenue | G8: Elizabeth · Wilson · Dennis
A9: Team | G9: Joan · Brian
A10: Person / Role | B10: Driving | C10: This week's commitment | D10: Actual / progress | E10: RAG | F10: Blocker | G10: Next action → owner | H10: Ask
A11: Dennis — Managing Director | B11: Partnerships
A12: Elizabeth — Head of Pipeline | B12: Revenue
A13: Wilson — Head of BD & Partnerships | B13: Programmes
A14: Joan — Chief of Staff | B14: Team
A15: Brian — Head of Technology | B15: Team
A16: Reds carried to Decision Log / decisions taken this week →
A18: WEEK 2 · w/c 06 Jul
A19: North Star | B19: RAG | C19: Where it stands (one line) | E19: This week's decisive move | G19: Lead(s)
A20: Programmes | B20: Amber | C20: Prisons presented but hit CAPEX pushback; CCIQ launch/readiness UNCONFIRMED on launch day; DMRV & telemetry not advanced. | E20: Get the LPG alternative to the Prisons Secretariat before their retreat; confirm CCIQ launch status. | G20: Wilson · Brian · Elizabeth
A21: Partnerships | B21: Amber | C21: KCB, Rockefeller & Equity meetings secured (good momentum); GEAPP CDMU submitted; but FSD signing slipping on undecided structure. | E21: Pin FSD to a decision and a date; hold KCB & RF meetings next week. | G21: Dennis · Wilson
A22: Revenue | B22: Amber | C22: Zero revenue closed; both anchor lines (Prisons $70–100k, Rockefeller $150k) still upstream. Early (W2), but nothing converted. | E22: Protect Prisons conversion; advance quick wins. (Dennis's numbers to confirm.) | G22: Elizabeth · Wilson · Dennis
A23: Team | B23: Amber | C23: Cockpit running, governance manual done, uptime clean — but the team is queued on Dennis (R6 live); ESCO not started. | E23: Clear the Dennis unblock-queue; ESCO restart 15 Jul. | G23: Joan · Brian
A24: Person / Role | B24: Driving | C24: This week's commitment | D24: Actual / progress | E24: RAG | F24: Blocker | G24: Next action → owner | H24: Ask
A25: Dennis — Managing Director | B25: Partnerships
A26: Elizabeth — Head of Pipeline | B26: Revenue | C26: Advance institutional pipeline; TECTONA launch prep; partner meetings (KCB, RF, Equity, Caritas) | D26: KCB & Rockefeller meetings secured for next week; Equity Bank first engagement done (awaiting intros); TECTONA budget negotiated to workable; WFP Uganda redirected to TESLA on scope. No revenue closed. | E26: Amber | F26: TECTONA stalled >14 days — awaiting Dennis budget sign-off + questionnaire feedback before data collection can start. | G26: 1) Dennis: sign off TECTONA budget + return questionnaire. 2) Dennis: facilitate Moses intro so Elizabeth takes over Caritas. 3) Elizabeth: hold KCB & RF meetings next week. | H26: Dennis: accelerate Sierra Leone/AfriGas next steps; facilitate the Caritas/Moses intro so I can drive it.
A27: Wilson — Head of BD & Partnerships | B27: Programmes | C27: Prisons TWG presentation; GEAPP CDMU deliverable | D27: Prisons TWG presented (steam cooking); GEAPP Compact Alignment & Measurable Outcome Map submitted. No new revenue closed. | E27: Amber | F27: Prisons: PS flagged CAPEX high vs competitors — needs detailed follow-up + groundwork before it converts. FSD: internal indecision on collaboration structure, no timeline. | G27: 1) Prisons follow-up pack (CAPEX/OPEX/O&M/risks/lessons) — Wilson. 2) Scope direct-LPG lower-CAPEX alternative — Dennis + Wilson. 3) Chase FSD structure decision — Wilson. | H27: Dennis: help scope a direct-LPG lower-CAPEX alternative for the Prisons Secretariat submission.
A28: Joan — Chief of Staff | B28: Team | C28: Governance manual; KIPI trademark; steam generator; data room; ESCO; cockpit | D28: People, Culture & Workplace Governance manual COMPLETED. KIPI trademark cleared — collecting Mon, filing next week. Steam generator delivered to BoilAfrica; KIRDI testing starts 10 Jul. Series A data room in progress (base documents assembled, compiling). Cockpit running. | E28: Green | F28: ESCO EPRA not started — restart set for 15 Jul. (Only open drag on the line.) | G28: ESCO EPRA visit by 15 Jul; continue compiling data room toward 31 Jul; collect trademark Mon + begin filing. | H28: (none named) — as CoS, batching and clearing the Dennis-unblock queue may be the real action here.
A29: Brian — Head of Technology | B29: Team | C29: Jikoni UI; content agents (LinkedIn/TikTok); platform uptime; (CCIQ launch readiness) | D29: LinkedIn posting bot stabilised; TikTok agent + Jikoni UI in build. No incidents; uptime clean. NO update on CCIQ platform / launch readiness — see flag. | E29: Amber | F29: Awaiting Outlook admin login credentials (blocks Outlook→Google Workspace migration). | G29: 1) Provide Outlook admin credentials — Joan. 2) Outlook→Workspace migration, Jikoni functionality, Instagram agent — Brian. 3) Report CCIQ platform / launch status — Brian. | H29: Claude subscription access (Dennis / Joan).
A30: Reds carried to Decision Log / decisions taken this week →
A32: WEEK 3 · w/c 13 Jul
A33: North Star | B33: RAG | C33: Where it stands (one line) | E33: This week's decisive move | G33: Lead(s)
A34: Programmes | B34: Amber | C34: Prisons: two costed scenarios built (integrated steam + direct LPG) — now sitting with Dennis for direction. KIRDI testing done. New positioning: IRENA (finance lead, Taita Taveta), WRI Energy ToR. CCIQ launch STILL unconfirmed (3rd week). | E34: Dennis to direct on the two Prisons scenarios before the Secretariat retreat; confirm CCIQ launch status. | G34: Wilson · Brian · Elizabeth
A35: Partnerships | B35: Amber | C35: Strong relationship week: KCB & Rockefeller meetings HELD, Mama Doing Good TWG convened, Practical Action 2027–30 consultation (ELMEC follow-up), UK PACT profiling. But FSD structure still undecided — 2nd week stalled. | E35: Escalate FSD to a decision and a date; schedule Practical Action / ELMEC follow-up. | G35: Dennis · Wilson
A36: Revenue | B36: Amber | C36: Second consecutive week with zero closed. CLASP ($10k) progressed but now gated on Ministry of Education curriculum approval. Prisons gated on Dennis. Both anchors (Prisons, Rockefeller $150k) still upstream. Week 3 of 13. | E36: Unblock Prisons direction; chase MoE on CLASP curriculum; convert at least one line. | G36: Elizabeth · Wilson · Dennis
A37: Team | B37: Amber | C37: Good delivery: TECTONA SLA SIGNED, governance manual V2, KIRDI testing done, data room progressing, domain/DNS/Workspace resolved. But the Dennis queue COMPOUNDED (all four leads waiting) and Dennis has not reported in W2 or W3. | E37: Clear the Dennis queue as a batch; get Dennis reporting; report data-room status. | G37: Joan · Brian
A38: Person / Role | B38: Driving | C38: This week's commitment | D38: Actual / progress | E38: RAG | F38: Blocker | G38: Next action → owner | H38: Ask
A39: Dennis — Managing Director | B39: Partnerships | D39: NO REPORT SUBMITTED (W2 and W3) | E39: Red | F39: No five lines received for a second week; several team items awaiting his direction. | G39: Submit CEO numbers + five lines; clear the unblock queue (Prisons scenarios, KIPI, card credentials, Makueni). | H39: —
A40: Elizabeth — Head of Pipeline | B40: Revenue | C40: CLASP; KCB & RF meetings; MDG TWG; TECTONA; partner positioning | D40: TECTONA SLA SIGNED. KCB & Rockefeller meetings held. Mama Doing Good TWG convened (strong CCIQ interest). Practical Action 2027–30 consultation — CCIQ positioned, ELMEC follow-up planned; IGNIS to be profiled to UK PACT. CLASP $10k progressed. No revenue closed. | E40: Green | F40: Makueni County stalled >14 days — no meeting date confirmed despite follow-up. CLASP now gated on MoE curriculum approval. | G40: Chase Makueni for a date; chase MoE on curriculum; schedule Practical Action/ELMEC follow-up. | H40: Dennis: availability for a Makueni meeting next week at short notice.
A41: Wilson — Head of BD & Partnerships | B41: Programmes | C41: Prisons cost scenarios; WRI ToR; IRENA; MDG TWG | D41: Prisons: two costed scenarios submitted to Dennis (integrated steam + direct LPG; firewood concessional vs open-market). WRI: drafted Energy ToR for National Clean Cooking Assessment. IRENA: Ignis positioned as finance lead using CCIQ for Taita Taveta school/SME pipeline. MDG TWG attended. No revenue closed; no big win reported. | E41: Amber | F41: FSD still stalled (2nd week) — blocker internal to FSD. Prisons scenarios now waiting on Dennis's direction. | G41: Dennis: direct on which scenario(s) to submit to the TWG Secretariat — time-critical vs their retreat. Wilson: chase FSD. | H41: Dennis: feedback on the two cost scenarios — which to submit, or present both.
A42: Joan — Chief of Staff | B42: Team | C42: KIRDI testing; governance manual V2; KIPI trademark; EPRA ESCO; data room (rolling) | D42: KIRDI testing DONE. Workplace Governance manual V2 DONE. Series A data room ONGOING and materially populated — company docs current incl. TCC, governance manual filed, EPRA ESCO + KIPI trademark registrations in flight (both feed the data room). | E42: Green | F42: KIPI go-ahead + EPRA support needed from Dennis. Registrations depend on external timelines (EPRA/KIPI). | G42: Define what 'data room live' means for 31 Jul (structured + populated, in-flight registrations flagged pending). Dennis: KIPI go-ahead + EPRA support. | H42: Dennis: go-ahead on KIPI trademark and support on EPRA registration.
A43: Brian — Head of Technology | B43: Team | C43: Domain transfer/DNS; Jikoni module; Workspace migration | D43: Domain acquired and added to Namecheap; Cloudflare set up and DNS records configured (fixed email issues from transfer). One Jikoni module completed. Google Workspace login now working — migration can proceed. | E43: Amber | F43: Awaiting Dennis's card credentials. No CCIQ platform / launch status reported (3rd consecutive week). No uptime line this week. | G43: Dennis: provide card credentials. Brian: complete Workspace migration + Jikoni module; report CCIQ platform status. | H43: Dennis: card credentials.
A44: Reds carried to Decision Log / decisions taken this week →
A46: WEEK 4 · w/c 20 Jul
A47: North Star | B47: RAG | C47: Where it stands (one line) | E47: This week's decisive move | G47: Lead(s)
A48: Programmes | B48: Amber | C48: Equity Group Foundation opens a major new line; IRENA submitted; C40/ECCA drafted; KIRDI done. Prisons has clear direction now (TCO 7-yr savings) — Dennis+Wilson finalising. CCIQ launch moved with its (postponed) event — not a gap. | E48: Land the Prisons TCO submission; scope Equity origination + LPG DMRV; set the CCIQ launch date once the event reschedules. | G48: Wilson · Brian · Elizabeth
A49: Partnerships | B49: Green | C49: Best week yet: FSD unstuck (working session 30 Jul); Equity Group Foundation at CEO level; Makueni MOU pathway agreed (signing ~2 wks); IRENA submitted; C40/ECCA; Practical Action profiling. Momentum broad — not yet conversion. | E49: Convert momentum: hold FSD 30 Jul session; land Makueni MOU; progress Equity faith-based proposal. | G49: Dennis · Wilson
A50: Revenue | B50: Amber | C50: Third consecutive week zero closed. Pipeline now rich (Equity, IRENA, Makueni, CLASP, Prisons) but nothing converted; CLASP gated on MoE approval; Prisons gated on Dennis. Week 4 of 13 — clock is the concern. | E50: Force a first conversion; unblock Prisons; land Makueni MOU within 2 weeks. | G50: Elizabeth · Wilson · Dennis
A51: Team | B51: Amber | C51: Strong delivery: TECTONA SLA closed, KIPI TM2 submitted, CCIQ TCs/Privacy drafted, Jikoni modules supported, KIRDI done, platform STABLE with CESA + docs uploaded. Dennis engaged (verbal updates). EPRA plan set (Wed visit). Outstanding: demo dates. | E51: Capture Dennis's updates into the cockpit; EPRA Wed visit; complete TECTONA signing + kickoff. | G51: Joan · Brian
A52: Person / Role | B52: Driving | C52: This week's commitment | D52: Actual / progress | E52: RAG | F52: Blocker | G52: Next action → owner | H52: Ask
A53: Dennis — Managing Director | B53: Partnerships | C53: Steering: Prisons, FSD, KCB, Sierra Leone, IRENA, TECTONA, C40, EPRA | D53: Captured from 20 Jul meeting (verbal). Prisons: added options, secured feedback to frame on Total Cost of Ownership (7+ yrs savings); finalising submission with Wilson this week. FSD: exchanging structure/fund-mgmt notes (wants faster). KCB: positioned Ignis as implementation platform (procurement/repayments/CS for a fee); proposal sent. Sierra Leone: founder wants capital moved before Nov summit — scheduling calls (Wed). IRENA (~$10k) submitted via consortium. TECTONA inputs added. EPRA: register as NESCo (heat+cool). C40: seeking Ethiopian partner. | E53: Green | F53: Throughput: many workstreams route through him; some (FSD) slower than he'd like. Not a report gap — updates come verbally. | G53: Joan to capture Dennis's meeting update into this row each week (no separate 5 lines needed). Delegate decision rights where possible. | H53: —
A54: Elizabeth — Head of Pipeline | B54: Revenue | C54: Equity concept note; Makueni; Practical Action; CLASP planning | D54: Equity Bank: faith-based schools concept note (Neema) developed, proposal in prep; chasing Equity–Dennis meeting via Eric. Makueni: successful meeting, MOU pathway agreed (signing ~2 wks) + joint workplan. Practical Action profiling interview. CLASP: student-attachment planning (Sam Omusala / Techwin). No revenue closed. | E54: Green | F54: Sierra Leone/AfriGas stalled >14 days — awaiting Dennis feedback/direction. | G54: Land Makueni MOU (2 wks); progress Equity proposal; Dennis to feed back on Sierra Leone. | H54: Dennis: feedback + pathway on Sierra Leone/AfriGas; availability for Makueni next week.
A55: Wilson — Head of BD & Partnerships | B55: Partnerships | C55: Prisons benchmarking; Equity Group Foundation; C40/ECCA; FSD; IRENA | D55: Prisons: benchmarked Chinese steam providers (still high) — shared with Dennis for direction. Equity Group Foundation: CEO-level exploratory meeting — positioning Ignis as origination+deployment engine via CCIQ + possible dMRV over their 238 sites; faith-based proposal (with Elizabeth) + dMRV LPG research near ready. C40/ECCA: Addis hospitality technical proposal + workplan drafted. FSD: working session secured 30 Jul. IRENA: proposal submitted (MECS, CCAK, Taita Taveta). No revenue closed. | E55: Green | F55: FSD no longer stalled (session 30 Jul). Prisons quote/approach waiting on Dennis. | G55: Dennis: direct on Prisons amounts/approach for TWG. Wilson: progress Equity + dMRV; run FSD 30 Jul session. | H55: Dennis: feedback on the Prisons TWG approach given the amounts we need to quote.
A56: Joan — Chief of Staff | B56: Team | C56: TECTONA close; KIPI TM2; Jikoni modules; CCIQ TCs; EPRA | D56: TECTONA SLA closed — signing + kickoff meeting remaining. KIPI: TM2 form submitted, awaiting response. Jikoni: authored module functional spec + clickable prototype and coordinated build (supported Brian on 2 modules). Drafted CCIQ Terms & Privacy Policy. EPRA not moved. | E56: Green | F56: EPRA: plan now in place — Wed visit with Dennis to register as NESCo (heating + cooling), not just electricity ESCO. CCIQ TCs/Privacy need team review. | G56: EPRA visit Wed (register heat+cool NESCo); team to review CCIQ TCs & Privacy; complete TECTONA signing + kickoff. | H56: Team: review the CCIQ Terms & Privacy Policy and share feedback.
A57: Brian — Head of Technology | B57: Team | C57: Jikoni modules; email + OneDrive migration; DNS | D57: Platform STABLE (confirmed independently). CESA agreements + built documents uploaded to CCIQ. Jikoni modules progressing (built to Joan's spec); Connect tool demo due this week. Email + OneDrive migration to Workspace underway; DNS fully propagated. | E57: Green | F57: No blocker on delivery. Outstanding: demo/walkthrough dates not yet sent (Jikoni + CCIQ platform review of uploaded docs) — asked at 20 Jul meeting, not yet converted. | G57: Send demo dates: Jikoni modules + CCIQ platform walkthrough (review uploaded CESA agreements & documents). | H57: (none named — reports would benefit from a blocker + 'commitments next week' line)
A58: Reds carried to Decision Log / decisions taken this week →
A60: WEEK 5 · w/c 27 Jul
A61: North Star | B61: RAG | C61: Where it stands (one line) | E61: This week's decisive move | G61: Lead(s)
A62: Programmes | B62: Amber | C62: IRENA countersigned (execution next week); C40 Addis submitted; DMRV moving (4RDigital carbon + LPG research); Jikoni landing. Prisons still awaiting Dennis; CCIQ launch pending event reschedule. | E62: Return Prisons direction; progress 4RDigital carbon framework; set CCIQ launch date. | G62: Wilson · Brian · Elizabeth
A63: Partnerships | B63: Green | C63: Strong 2nd green week: FSD 30 Jul session landed with distributed ownership + methodology doc; Equity MOU reviewed (circulating); Makueni workplan done (MOU pathway); IRENA consortium; 4RDigital scoped; Practical Action profiling. KCB (Eric) the one lag. | E63: Land Makueni + Equity MOUs once Dennis clears; deliver FSD methodology doc; secure KCB–Dennis meeting. | G63: Dennis · Wilson
A64: Revenue | B64: Amber | C64: FIRST signed engagement (IRENA countersigned, ~$10–15k) — streak broken. But small vs $100k floor; anchors (Prisons, Rockefeller) still upstream; CLASP with MoE. Week 5 of 13. | E64: Convert an anchor; layer signed engagements toward the floor; size burn/runway from July reconciliation. | G64: Elizabeth · Wilson · Dennis
A65: Team | B65: Green | C65: Best Team week: Jikoni landing (demo Fri), TECTONA signed, EPRA started + permit, July expenses reconciled, UNDP DD, Finance & Travel Guidelines, Claude set up, governance done. Cockpit cadence holding. Dennis's line to be captured at next meeting. | E65: Land Jikoni (Wed); complete EPRA + UNDP DD; capture Dennis's update into the cockpit. | G65: Joan · Brian
A66: Person / Role | B66: Driving | C66: This week's commitment | D66: Actual / progress | E66: RAG | F66: Blocker | G66: Next action → owner | H66: Ask
A67: Dennis — Managing Director | B67: Partnerships
A68: Elizabeth — Head of Pipeline | B68: Revenue | C68: Makueni workplan; Equity MOU; 4RDigital dMRV; FSD tasks; TECTONA | D68: Makueni implementation workplan COMPLETED; Equity Bank MOU reviewed — both to circulate this week (pending Dennis clearance). 4RDigital scoping session held — carbon dMRV collaboration scoped; framework design next. FSD: leading pipeline extract + aligning TECTONA survey to FSD methodology + supporting bank diagnostic. TECTONA to inception this week (field data from 10 Aug). Practical Action profiling feedback due. | E68: Green | F68: KCB stalled — still chasing Eric for a KCB–Dennis meeting. Mama Doing Good — awaiting next TWG date. | G68: Circulate Makueni workplan + Equity MOU once Dennis clears; progress 4RDigital framework; run FSD pipeline extract; chase Eric (KCB) + MDG date. | H68: Dennis: review & clear the final Makueni workplan and Equity Bank MOU for onward sharing.
A69: Wilson — Head of BD & Partnerships | B69: Partnerships | C69: IRENA; FSD 30 Jul session; C40; Equity; Prisons | D69: IRENA: proposal ACCEPTED + project agreement COUNTERSIGNED — execution starts next week (Gamos/MECS, CCAK, Taita Taveta). FSD: 30 Jul session held — additionality, bank engagement, flow-of-funds, fund-mgmt progressed, next steps + owners set; Wilson leading methodology doc + Bank Experience Diagnostic. C40/ECCA Addis: technical+financial proposal submitted. Equity faith-based proposal + LPG dMRV research in final edits. | E69: Green | F69: Prisons: no movement — quotation breakdown still with Dennis. | G69: Lead FSD methodology doc + diagnostic (with Elizabeth, Joan); finalise Equity proposal + LPG dMRV; mobilise IRENA. Dennis: Prisons feedback. | H69: (none this week)
A70: Joan — Chief of Staff | B70: Team | C70: TECTONA; EPRA+permit; July expenses; UNDP DD; Finance & Travel guidelines; Jikoni; CCIQ T&Cs | D70: TECTONA SLA SIGNED — kickoff Tue. EPRA registration starting + business permit. July expenses reconciled. Working on UNDP due-diligence documents. Company Finance & Travel Guidelines drafted. Supported Brian on Jikoni build — demo held Fri; most modules built; fully running by Wed EOD. CCIQ T&Cs + Privacy drafted (team review pending). [UNDP DD, expenses & guidelines feed the data room.] | E70: Green | F70: CCIQ T&Cs/Privacy still awaiting team review (raised 2nd week). | G70: Run TECTONA kickoff Tue; complete EPRA + permit; land Jikoni (Wed EOD); finish UNDP DD; chase team on T&Cs/Privacy review. | H70: Team: review the CCIQ Terms & Privacy Policy and share feedback.
A71: Brian — Head of Technology | B71: Team | C71: Jikoni ERP modules; Claude setup | D71: Jikoni ERP: initial modules set up (demo held Fri with Joan; fully running Wed EOD). Set up Claude for the team. Platform stable. Next: complete remaining Jikoni modules; add team members to Claude. | E71: Green | F71: No blockers. (Report still light on uptime / CCIQ platform line — schedule the platform walkthrough.) | G71: Complete remaining Jikoni modules; add team to Claude; schedule CCIQ platform walkthrough of uploaded docs. | H71: (none — Claude access resolved by setting it up)
A72: Reds carried to Decision Log / decisions taken this week →
A74: WEEK 6 · w/c 03 Aug
A75: North Star | B75: RAG | C75: Where it stands (one line) | E75: This week's decisive move | G75: Lead(s)
A76: Programmes | B76: Amber | C76: IRENA formally underway (6-mo project, 4 stages); DMRV advancing (4RDigital carbon + Equity LPG dMRV V1); CIFF/WRI AssetCo pilot plan off FSD architecture; Sierra Leone regional (First Lady Nov). Brian building CCIQ Taita Taveta instance. PRISONS status unknown; CCIQ launch pending event. | E76: Answer the Prisons question; run AssetCo institution visits; progress DMRV frameworks; set CCIQ launch date. | G76: Wilson · Brian · Elizabeth
A77: Partnerships | B77: Green | C77: Strong 3rd green week: FSD MoU drafting with ROLES DEFINED (architect/anchor investor vs originator/operator/dMRV owner); Equity V1 submitted; IRENA consortium aligned; Coop Bank/Foundation opened; Makueni workplan approved; 4RDigital scoped. Lags: KCB (Eric), Machakos (County Attorney). | E77: Execute the FSD MoU; clear Equity MOU (Dennis); land Makueni meeting; carry Coop Bank forward. | G77: Dennis · Wilson
A78: Revenue | B78: Amber | C78: No NEW revenue closed this week. IRENA underway (only signed engagement, ~6-mo). Path to $100k floor now uncertain: Prisons (biggest line) status unknown; Rockefeller upstream; CLASP with MoE. Week 6 of 13 — half the quarter gone, floor not yet in sight. | E78: Resolve Prisons; convert Rockefeller or an anchor; size burn/runway; layer signed engagements. | G78: Elizabeth · Wilson · Dennis
A79: Team | B79: Green | C79: Best Team week: FIRST full 5/5 reporting (Dennis async first time); Jikoni LIVE; Claude rolled out + team onboarded; SharePoint→Drive done; business permit; EPRA started; DREEM + UNDP DD + Finance guidelines; coordinated CCIQ costing split. Cadence fully landed. | E79: Close EPRA + KIPI; maintain 5/5 cadence; keep systems + compliance moving. | G79: Joan · Brian
A80: Person / Role | B80: Driving | C80: This week's commitment | D80: Actual / progress | E80: RAG | F80: Blocker | G80: Next action → owner | H80: Ask
A81: Dennis — Managing Director | B81: Partnerships | C81: IRENA; Sierra Leone; Coop Bank; FSD; CIFF/WRI AssetCo; TECTONA; Ops | D81: [First async report submitted.] IRENA countersigned Aug 3, kickoff Aug 7 (formally underway); tasked Brian with CCIQ instance for Taita Taveta (demo Mon). Sierra Leone: plan agreed — regional convening + in-country CCIQ + First Lady convening (Freetown, Nov). Coop Bank/Foundation: new conversations opened. FSD: heading to MoU. CIFF/WRI: AssetCo pilot plan off FSD architecture; institution visits next to pick cohort. TECTONA: reworked + returned consent/data-protection docs to Elizabeth. Ops: SharePoint→Drive, Workspace billing, Claude Team rollout with 1:1 onboarding. | E81: Green | F81: None flagged. (Equity MOU + Makueni meeting still await his action per Elizabeth.) | G81: Sierra Leone First Lady's office meeting; CIFF/WRI institution visits; model AssetCo contract; clear Equity MOU; watch World Bank/GEAPP calls. | H81: —
A82: Elizabeth — Head of Pipeline | B82: Revenue | C82: Makueni; Equity MOU; TECTONA; 4RDigital; IRENA; Sierra Leone | D82: Makueni workplan approved & shared with Naomi (awaiting review meeting). Equity MOU ready for final internal feedback (sharing this week). TECTONA moved contracting→implementation; field data now 31 Aug (schools reopen 24 Aug). IRENA kickoff done — IGNIS to leverage CCIQ + A2CT data for investable portfolios (Taita Taveta). 4RDigital scope defined; next meeting firms timelines. Sierra Leone diagnostic progressed — regional West Africa questionnaire next. | E82: Green | F82: Makueni (awaiting meeting date); Machakos MOU with County Attorney (follow up); Equity MOU awaiting Dennis final feedback. | G82: Share Equity MOU + TECTONA package once Dennis clears; prep enumerator training (field data 31 Aug); chase Makueni meeting + Machakos; firm 4RDigital timelines. | H82: Dennis: final clearance on Equity MOU + TECTONA data-protection/consent/questionnaire docs.
A83: Wilson — Head of BD & Partnerships | B83: Partnerships | C83: FSD MoU; IRENA kickoff; Equity V1; CCIQ costing | D83: FSD: received 30 Jul notes/presentation + notice of draft MoU; MoU drafting underway with ROLES DEFINED — FSD as transaction architect/anchor catalytic investor, Ignis/CCIQ as originator, platform operator & dMRV owner. IRENA: formal kickoff — 6-month project (through 31 Jan 2027), 4 stages; Kavita (IRENA) visits Kenya 30 Aug. Equity: faith-based proposal + LPG dMRV research submitted V1 for team feedback. CCIQ costing sync — work split by fuel (Wilson: firewood/charcoal + briquettes). No revenue closed. | E83: Green | F83: None flagged. NOTE: Prisons unmentioned again — owner is Wilson; status now unknown (see decision log). | G83: Advance FSD MoU; run IRENA next steps (A2CT data review, data-gaps session, late-Aug workshop); collect Equity V1 feedback. CONFIRM Prisons status. | H83: (none this week)
A84: Joan — Chief of Staff | B84: Team | C84: Business permit; EPRA; Jikoni; DREEM application; CCIQ costing (biogas) | D84: Business permit obtained. EPRA application started (ongoing). Jikoni live (supported build; now in production). DREEM application started (ongoing). Owning biogas scenario in CCIQ costing work-split. | E84: Green | F84: None flagged. | G84: Close EPRA; follow up KIPI trademark; close Claude with Brian; close DREEM application. | H84: —
A85: Brian — Head of Technology | B85: Team | C85: Jikoni live; Claude+Workspace; onboarding; SharePoint migration | D85: Jikoni tool FINALISED — live/working in production. Claude integrated with Workspace (Drive, Gmail, Calendar). Team onboarded onto Claude + access setup. SharePoint documents migrated to Drive. Next: CCIQ instance for Taita Taveta (demo Mon). | E85: Green | F85: None. (CCIQ platform walkthrough of uploaded docs still to schedule.) | G85: Stand up CCIQ instance for Taita Taveta (demo Mon); schedule CCIQ platform walkthrough. | H85: (none)
A86: Reds carried to Decision Log / decisions taken this week →
A88: WEEK 7 · w/c 10 Aug
A89: North Star | B89: RAG | C89: Where it stands (one line) | E89: This week's decisive move | G89: Lead(s)
A90: Programmes | B90: Amber | C90: IRENA/Taita DELIVERING — baseline analysis (409 records) commended, shortlist of 8+8 underway. Prisons RESUMED (procurement advocacy). AssetCo model maturing across FSD/CIFF-WRI/Zambia. CCIQ Taita instance live; website in build. Delivery is structuring, not yet deploying; launch pending. | E90: Advance IRENA shortlisting + convening; progress AssetCo pilots; set CCIQ launch date. | G90: Wilson · Brian · Elizabeth
A91: Partnerships | B91: Green | C91: Strong 4th green week: FSD MoU tracked-changes with FSD since 15 Aug — signing 17–18 Aug (IP/Non-Circ/Data-Protection clauses added by Joan); Gamos/Ignis MOU; Zambia/CES structure; Mercy Corps Intent-to-Bid; IRENA consortium delivering. | E91: SIGN the FSD MoU (17–18 Aug); action IRENA sub-agreement; carry Zambia/CES + Mercy Corps forward. | G91: Dennis · Wilson
A92: Revenue | B92: Amber | C92: $11K signed of $100K floor this week: IRENA + CCAK confirmed at $8,000 (revised down from the earlier $15,000 estimate) plus a new, separate $3,000 short-term energy consultancy (Dennis). Financial Model v1 done. Prisons and Rockefeller ($150k) remain the two big unconverted anchors. | E92: State burn/runway from the Financial Model; force one big close; decide on the floor target. | G92: Elizabeth · Wilson · Dennis
A93: Team | B93: Green | C93: 3rd green week: full reporting (Elizabeth excused); Jikoni live; Taita CCIQ stood up; website in build; heavy deal documentation (FSD workplan, CESA v7, Gamos MOU); DREEM finalised; EPRA + KIPI ongoing. | E93: Close EPRA + KIPI; hold cadence; keep deal docs + systems moving. | G93: Joan · Brian
A94: Person / Role | B94: Driving | C94: This week's commitment | D94: Actual / progress | E94: RAG | F94: Blocker | G94: Next action → owner | H94: Ask
A95: Dennis — Managing Director | B95: Revenue | C95: Revenue/Financial Model; FSD MoU; Taita/CCIQ; KCB; WRI/CIFF retreat | D95: $3K CLOSED vs $100K Q3 target (first hard figure). Ignis Financial Model v1 DONE — end-to-end view of institution-business revenue streams. FSD MoU advanced (signing 17–18 Aug). Taita Taveta data in hand; CCIQ instance stood up (IRENA/Gamos/CCAK). Priorities: KCB, Harun LPO, WRI/CIFF clean-cooking retreat, West Africa follow-up. | E95: Green | F95: None flagged. | G95: Sign FSD MoU (17–18 Aug); KCB conversation; WRI/CIFF retreat; use Financial Model to size burn/runway + revenue path. | H95: —
A96: Elizabeth — Head of Pipeline | B96: Revenue | D96: No report — unwell this week (excused). | E96: Not Started
A97: Wilson — Head of BD & Partnerships | B97: Partnerships | C97: Prisons advocacy; IRENA/Taita analysis; FSD MoU; CESA v7; Mercy Corps; Zambia/CES | D97: PRISONS RESUMED — pivoted from direct bid to procurement advocacy: Treasury letter (12 Aug) demanding baseline data, technology-neutral competitive procurement (PPADA), lifecycle costing — positions Ignis's approach as the standard. IRENA/Taita: baseline analysis presented (409 records, 4 categories); Gamos commended; shortlist of 8 institutions + 8 SMEs; weekly check-in (next 21 Aug). FSD: 90-day workplan received; MoU signing 17–18 Aug. CESA v7 (Joan) now with Wilson to condense 27→15pp. Mercy Corps HQ749 Intent-to-Bid submitted. Zambia/CES collaboration (CCIQ SaaS / Ignis AssetCo / CES financier). | E97: Green | F97: None — Prisons resumed via advocacy; IRENA sub-agreement has 2 comments pending team input. | G97: Condense CESA to ~15pp; action IRENA sub-agreement; compile CES needs doc + find Zambia co-funder (20 Aug); progress FSD MoU signing. | H97: (none this week)
A98: Joan — Chief of Staff | B98: Team | C98: FSD 90-day workplan; CESA v7; Gamos MOU; DREEM; EPRA; KIPI | D98: Prepared FSD–Ignis 90-day workplan (shared with Wilson). FSD MoU: added 3 new clauses (IP, Non-Circumvention, Data Protection) on top of Dennis's — Dennis sent the tracked-changes version to FSD's Robert Akunga on 15 Aug; signing targeted 17–18 Aug. Prepared CESA v7 (Dennis's 4 changes) → shared with Wilson to condense. Reviewed Gamos/Ignis MOU. DREEM application FINALISED & shared. EPRA ESCO ongoing. Trademark T2 ongoing (awaiting KIPI). | E98: Green | F98: KIPI feedback awaited (trademark). EPRA registration still to close. | G98: Close EPRA; chase KIPI trademark; support FSD MoU signing (17–18 Aug) + CESA finalisation. | H98: —
A99: Brian — Head of Technology | B99: Team | C99: Jikoni subdomain/live; Taita on CCIQ; website demo | D99: Configured Jikoni subdomain; pushing Jikoni to live. Set up Taita Taveta programme on CCIQ + invited team. Website draft demo Monday. Next: website development + push to live. | E99: Green | F99: None. (CCIQ platform walkthrough of uploaded docs still to schedule.) | G99: Push Jikoni live; website demo Mon → develop + push live; support Taita CCIQ processing. | H99: (none)
A100: Reds carried to Decision Log / decisions taken this week →
A102: WEEK 8 · w/c 17 Aug
A103: North Star | B103: RAG | C103: Where it stands (one line) | E103: This week's decisive move | G103: Lead(s)
A104: Programmes | C104: RAG UNSET — 2 of 5 reported. Voi convening (26 Aug) restructured to one integrated day with a Financing Forum; Tectona fieldwork rerouted, Mui MoU still delayed; DMRV at risk after 4RDigital deferral. Nothing heard on CCIQ or platform. | E104: Deliver Voi convening (26 Aug); get KOBO + ToT status; re-date the DMRV target. | G104: Wilson · Brian · Elizabeth
A105: Partnerships | C105: RAG UNSET — the deciding fact is missing: FSD MoU signature targeted 17–18 Aug, unconfirmed either way. Elsewhere strong: CESA at 14pp with one open item; IRENA sub-agreement cleared to execute; Zambia/CES priorities agreed (call 3 Sep). | E105: Yes or no on the FSD MoU from Dennis; close CESA Annex A (25 Aug); execute IRENA sub-agreement. | G105: Dennis · Wilson
A106: Revenue | C106: RAG UNSET — no new close; holds at $11K of the $100K floor at wk 8/13. Dennis and Elizabeth, who own every remaining line, did not report. Restated FY26 financials now in hand — burn/runway can finally be stated. | E106: Put burn/runway on the home tab; take the $100K floor decision with Dennis. | G106: Elizabeth · Wilson · Dennis
A107: Team | C107: RAG UNSET — reporting fell to 2 of 5, worst of the quarter and the first with 3 unexcused misses including the MD. Output from the two who reported was strong: CESA 27→14pp, FY26 review owned, WHT filed, ELMECC interview. Cadence slipped, not work. | E107: Reset the five-line expectation with Dennis, Elizabeth and Brian before the next cockpit. | G107: Joan · Brian
A108: Person / Role | B108: Driving | C108: This week's commitment | D108: Actual / progress | E108: RAG | F108: Blocker | G108: Next action → owner | H108: Ask
...

Sheet 4. Scorecard
A1: SCORECARD — Q3 2026
A2: Fixed quarter targets under the four north stars · the run-sheet is the weekly pulse; this is the target ledger
A4: Target / Key Result | B4: Owner | C4: Due / Amount | D4: RAG | E4: This week — progress / evidence | F4: Notes
A5: PROGRAMMES — what the money builds & delivers
A6: Prisons technology slot won + payment terms confirmed | B6: Wilson | C6: 7 Jul / 31 Jul | D6: Amber | E6: RESUMED as procurement advocacy (Treasury letter) — reframing to technology-neutral competitive process; revenue timing uncertain | F6: Also Revenue ($70–100k)
A7: CCIQ platform launched (launch-ready by 9 Jul) | B7: Dennis (acc.) / Wilson | C7: 9 Jul | D7: Amber | E7: CESA Institution facing agreement cut from 27 to 14 pages plus 3 schedules (18 Aug), one open item; Taita instance live; no platform or launch update received in W8 | F7: Launch PMO off Joan; Dennis accountable, Wilson logistics, Brian tech-readiness
A8: Uganda market entry — entity registered | B8: Wilson | C8: 15 Aug | D8: Amber | E8: Entry scoping; entity not yet registered | F8: Also Revenue ($20k)
A9: Sierra Leone — 20 schools licensed · SEforALL EPC RFP | B9: Wilson / Dennis | C9: Q3 | D9: Amber | E9: Founder traction (Nov Sierra Leone summit); calls being scheduled | F9: Also Revenue (TBD)
A10: Household Programme pilot structure defined (investor-ready) | B10: Elizabeth | C10: 30 Sep | D10: Amber | E10: Early; induction-cooker testing feeds household learnings
A11: DMRV provider selected & contracted | B11: Wilson / Brian | C11: 31 Aug | D11: Red | E11: AT RISK for 31 Aug: 4R Digital platform decision deferred (18 Aug) pending hardware manufacturing; GSM remote control still needed | F11: Technical + commercial
A12: IEA Summit narrative & market positioning | B12: Dennis | C12: Q3 | D12: Not Started
A13: PARTNERSHIPS — the six strategic relationships
A14: FSD Africa: signed & publicly announced | B14: Wilson / Dennis | C14: 9 Jul | D14: Amber | E14: Signature targeted 17 to 18 Aug, NOT CONFIRMED by anyone in W8; tracked changes MoU with FSD since 15 Aug
A15: Rockefeller + CIFF: concept note -> MOU / LOI | B15: Elizabeth | C15: 31 Aug | D15: Amber | E15: RF meeting held; concept note advancing | F15: FLAG: concept-note 4 Jul vs 31 Jul — reconcile
A16: GEAPP / Mission 300: CDMU proposal submitted | B16: Elizabeth / Wilson | C16: 31 Jul | D16: Amber | E16: CDMU alignment map submitted; formal proposal date TBC | F16: FLAG: 31 Jul vs 31 Aug — reconcile
A17: KCB: joint call held + next step agreed | B17: Elizabeth | C17: 31 Jul | D17: Amber | E17: Positioned as implementation platform; still chasing Eric for the KCB–Dennis meeting
A18: Caritas: MOU / data-sharing agreement signed | B18: Elizabeth | C18: 31 Aug | D18: Amber | E18: In pipeline; MOU not yet advanced
A19: AfDB: formal engagement letter / MOU | B19: Wilson | C19: 30 Sep | D19: Not Started
A20: Anchor funder conversation active (named contact + next step) | B20: Dennis | C20: 30 Sep | D20: Amber | E20: Multiple funder conversations active; no single anchor locked
A21: Equity Bank (Julius) relationship advanced | B21: Elizabeth | C21: Q3 | D21: Green | E21: Equity Bank invited into the 26 Aug Voi financing session alongside KCB, Qwetu SACCO, Caritas Microfinance and Co operative Bank
A22: 15 CCIQ solution providers onboarded | B22: Wilson | C22: 30 Sep | D22: Not Started
A23: REVENUE — all money in · $100,000 floor (full $ tracker on Cockpit home)
A24: Prisons | B24: Wilson | C24: $70k–100k | D24: Amber | E24: In progress; no $ closed yet | F24: Wilson
A25: Rockefeller | B25: Elizabeth | C25: $150k | D25: Amber | E25: Meeting held; upstream | F25: Elizabeth
A26: CLASP | B26: Elizabeth | C26: $10k | D26: Amber | E26: Curriculum with Ministry of Education for approval; attachments planning | F26: Elizabeth
A27: UNDP | B27: Elizabeth | C27: TBD | D27: Not Started | E27: Amount TBC | F27: Elizabeth — amount to confirm
A28: IRENA + CCAK | B28: Dennis | C28: $8k (confirmed, revised from $15k est.) | D28: Green | E28: Sub agreement cleared by Dennis 16 Aug, ready to execute with Gamos; 26 Aug Voi convening restructured to one integrated full day with a Financing Forum session | F28: Dennis
A29: Uganda | B29: Dennis | C29: $20k | D29: Amber | E29: Scoping | F29: Dennis
A30: Sierra Leone (20 schools licensed) | B30: Dennis | C30: TBD | D30: Amber | E30: Founder traction | F30: Dennis — amount to confirm
A31: TEAM — ownership, cadence, systems, compliance
A32: Weekly cockpit runs 12 of 13 weeks, facilitated by Joan | B32: Joan | C32: Weekly | D32: Amber | E32: Running weekly; W8 reporting fell to 2 of 5 (Wilson, Joan) with three unexcused misses | F32: This instrument
A33: Every person completes >=1 deal / partnership without Dennis | B33: All | C33: 30 Sep | D33: Amber | E33: In progress across the team
A34: No pipeline item stalled >14 days without a named action | B34: All (Joan tracks) | C34: Ongoing | D34: Green | E34: Cockpit catching & actioning stalls
A35: Series A data room live | B35: Joan | C35: 31 Jul | D35: Amber | E35: Ongoing, materially populated; 'live' definition set for 31 Jul | F35: Define 'live' for 31 Jul: structured + populated, in-flight registrations flagged pending
A36: Corporate compliance — KIPI · ESCO EPRA visit · policies manual | B36: Joan | C36: 31 Jul | D36: Amber | E36: Withholding tax filed (W8); induction cookstoves collected from KIRDI; EPRA ESCO and KIPI T2 unchanged this week; restated FY26 financials received 20 Aug | F36: ESCO w/o 30 Jun
A37: Tectona data-collection partnership signed | B37: Elizabeth | C37: 15 Jul | D37: Done | E37: SLA signed; kickoff Tue | F37: Elizabeth owns end to end. W8: forms corrected to Tectona Group Limited; Mui County MoU delayed; enumerator manual circulated 20 Aug
A38: Jikoni internal OS — CRM + ERP modules live | B38: Brian | C38: 31 Jul | D38: Done | E38: LIVE in production (confirmed W6)
A39: Platform go/no-go · docs uploadable · CRM fix live | B39: Brian | C39: 4 Jul | D39: Green | E39: CRM fixed; docs uploaded; platform stable
A40: IoT telemetry live on all new Q3 units | B40: Brian | C40: Q3 | D40: Not Started
A41: LinkedIn AI content agent live | B41: Brian | C41: Q3 | D41: Green | E41: LinkedIn bot stabilised / live

Sheet 5. Milestones
A1: MILESTONES — JULY CRITICAL PATH + PARTNER TARGETS
A2: Anchors: 7 Jul (Prisons) · 9 Jul (CCIQ launch + FSD signing) · 26 Sep (Q3 close)
A4: Date | B4: Milestone | C4: Owner | D4: Status | E4: Note
A5: 30 Jun | B5: Tax filing · Tectona call · CRM fix live | C5: Joan / Brian | D5: Done | E5: CRM live; TECTONA call held; tax filed
A6: 1 Jul | B6: Q3 roadmap shared · Uganda update from Wilson | C6: Dennis | D6: Done | E6: Q3 roadmap shared
A7: 2 Jul | B7: All CCIQ registration documents live & tested | C7: Brian | D7: Done | E7: CCIQ registration docs uploaded (walkthrough pending)
A8: 4 Jul | B8: FSD terms finalised · RF concept note revised · CCIQ go/no-go signed off | C8: Wilson | D8: At Risk | E8: FSD terms not finalised (→ 30 Jul session); launch event postponed
A9: 6 Jul | B9: Prisons deck complete & rehearsed · GEAPP budget proposal ready | C9: Wilson | D9: Done | E9: Prisons deck done & rehearsed; GEAPP budget work done
A10: 7 Jul | B10: ANCHOR: Prisons technology presentation — steam cooking via Kitchenerra (08:00) | C10: Wilson | D10: Done | E10: Presented 7 Jul; now in TCO rework
A11: 8 Jul | B11: Makueni County TWG in person · GEAPP follow-up meeting | C11: Elizabeth | D11: On Track | E11: Makueni MOU pathway agreed; GEAPP progressing
A12: 9 Jul | B12: ANCHOR: CleanCookIQ launch + FSD Africa partnership signing (virtual) | C12: Dennis | D12: On Track | E12: FSD 30 Jul session held — strong progress; methodology doc + diagnostic next
A13: 11 Jul | B13: KCB-Rockefeller-Ignis call · DMRV comparison table complete | C13: Elizabeth | D13: On Track | E13: KCB & RF meetings held; DMRV research ongoing
A14: 15 Jul | B14: ESCO EPRA visit (compliance) — restart of item that was due w/o 30 Jun | C14: Joan | D14: On Track | E14: EPRA application started; business permit obtained; closing next week
A15: TBC | B15: CCIQ platform + Jikoni demo — walk through uploaded CESA agreements & documents | C15: Brian | D15: On Track | E15: Jikoni demo held Fri (fully running Wed); CCIQ platform walkthrough still to schedule
... A20: 3 Sep | B20: Zambia/CES joint call — PUE investment, IoT monitoring and verification, market based Lusaka pilots | C20: Dennis / Wilson | D20: On Track | E20: Three priority areas agreed with Nitin Akhade (CES)
A21: 26 Sep | B21: Q3 CLOSE — score north stars honestly, set Q4 · $100K floor · household pilot structure defined | C21: All | D21: Not Started

Sheet 6. Decision Log
A1: DECISION LOG
A2: Every red item leaves the meeting here — named owner + next action. Accumulates all quarter.
A4: # | B4: Week | C4: Red item / issue | D4: Decision / next action | E4: Owner | F4: Due | G4: Status | H4: Date closed
A5: 1 | C5: RF concept note due-date conflict (Partnerships: 31 Aug MOU, but concept-note 4 Jul vs 31 Jul) | D5: Agree single date; update Scorecard + Milestones | E5: Elizabeth | F5: 4 Jul | G5: Open
A6: 2 | C6: GEAPP CDMU proposal due-date conflict (31 Jul vs 31 Aug) | D6: CDMU alignment map submitted (W2) — date conflict moot | E6: Joan | F6: 11 Jul | G6: Closed
A7: 3 | C7: DMRV provider not yet selected (feeds Programmes: household + institutional) | D7: Superseded — DMRV advancing (4RDigital carbon + LPG V1); tracked in R7 | E7: Wilson | F7: 31 Aug | G7: Closed
A8: 4 | C8: UNDP & Sierra Leone revenue amounts still TBD | D8: Confirm $ figures; update Revenue tracker | E8: Elizabeth / Dennis | F8: 31 Jul | G8: Open
A9: 5 | B9: W2 | C9: Prisons ($70–100k anchor) — RESOLVED: not dead, RESUMED as procurement advocacy | D9: Wilson pivoted to a Treasury advocacy letter (12 Aug) challenging the procurement to force technology-neutral competitive process + baseline data. Near-term revenue timing now uncertain, but strategically stronger. | E9: Joan → Wilson/Dennis | F9: before next mtg | G9: Closed
A10: 6 | B10: W2 | C10: TECTONA data collection stalled >14 days — blocked on Dennis | D10: RESOLVED: TECTONA SLA signed by Elizabeth (W3). Data collection can proceed. | E10: Dennis | F10: before 15 Jul | G10: Closed | H10: W3
A11: 7 | B11: W2 | C11: TECTONA ownership unclear — on Joan's Scorecard line, but Elizabeth is driving it | D11: RESOLVED: Elizabeth owns TECTONA end-to-end; Joan tracks. Budget sign-off is now Elizabeth's ask of Dennis. (Reconcile 15 Jul vs 31 Jul date.) | E11: Elizabeth | F11: first cockpit | G11: Closed
A12: 8 | B12: W2 | C12: CCIQ launch status UNCONFIRMED on launch day (9 Jul) — no readiness/launch update from tech or PMO | D12: Resolved — launch tied to an external event that was postponed; R4 de-escalated | E12: Dennis / Brian | F12: today | G12: Closed
A13: 9 | B13: W3 | C13: Prisons ($70–100k anchor) UNREPORTED by Dennis, Elizabeth AND Wilson (owner) in W6 — status unknown after a month as top revenue concern | D13: Duplicate of the active Prisons flag — consolidated | E13: Joan → Wilson/Dennis | F13: before next mtg | G13: Closed
A14: 10 | B14: W3 | C14: Dennis reports verbally in the meeting (leads it), not via async five lines | D14: RESOLVED: Joan captures Dennis's meeting update into his cockpit row each week — no separate five-line report required. | E14: Joan / Dennis | F14: first cockpit | G14: Closed
A15: 11 | B15: W3 | C15: CCIQ launch status still unconfirmed 3 weeks after launch date (9 Jul) | D15: Resolved — launch event postponed (duplicate) | E15: Dennis / Brian | F15: this week | G15: Closed
A16: 12 | B16: W3 | C16: 'Data room live by 31 Jul' undefined — some contents (EPRA ESCO, KIPI trademark) depend on external timelines | D16: Define 'live' as: structured, permissioned and populated with all existing docs; in-flight registrations flagged as pending | E16: Joan | F16: 31 Jul | G16: Open
A17: 13 | B17: W4 | C17: CCIQ Terms & Conditions and Privacy Policy drafted — need team review before publish | D17: Team to review CCIQ T&Cs + Privacy Policy — raised again W5, still outstanding | E17: All (Joan owns) | F17: next week | G17: Open
A18: 14 | B18: W4 | C18: Sierra Leone/AfriGas stalled >14 days — awaiting Dennis feedback/direction | D18: Sierra Leone now active — plan agreed, First Lady convening Nov; AfriGas folded into programme | E18: Dennis | F18: this week | G18: Closed
A19: 15 | B19: W4 | C19: CCIQ platform walkthrough of uploaded CESA docs still to schedule | D19: Jikoni demo HELD Fri (fully running Wed EOD). Remaining: schedule the CCIQ platform walkthrough of uploaded documents. | E19: Brian | F19: this week | G19: Open
A20: 16 | B20: W5 | C20: July company expenses reconciled — burn/runway now known | D20: Inputs now complete: Financial Model v1 plus the restated FY26 financials (P&L, Balance Sheet, Cash Flow, Equity, Notes) received 20 Aug. Next step is a single headline burn or runway figure on the home tab. | E20: Joan | F20: before next cockpit | G20: Open
A21: 17 | B21: W5 | C21: Equity MOU awaiting Dennis final feedback before external sharing (Makueni workplan now approved & shared) | D21: Dennis clears Equity MOU + TECTONA package this week so Elizabeth can share & prep enumerator training. TECTONA consent/data-protection docs already reworked & returned by Dennis. | E21: Dennis | F21: this week | G21: Open
A22: 18 | B22: W8 | C22: FSD MoU signature UNCONFIRMED. Signing was targeted 17 to 18 Aug; neither reporter could confirm it happened. | D22: Dennis to confirm signed or not signed, and if not, the new date. This single fact sets the Partnerships RAG and closes or reopens R9. | E22: Dennis (Joan chases) | F22: before next cockpit | G22: Open
A23: 19 | B23: W8 | C23: CESA: one open item left, the Annex A tariff adjustment cap, blocking sign off of the 14 page Core Agreement. | D23: Finalisation working session 25 Aug to settle the cap figure, then move to sign off. | E23: Wilson / Joan | F23: 25 Aug | G23: Open
A24: 20 | B24: W8 | C24: Reporting collapsed to 2 of 5. Dennis, Elizabeth and Brian did not report for w/c 17 Aug, none excused. | D24: Reset the expectation directly with each of the three before the next cockpit. Elizabeth is now two weeks without a report (W7 excused, W8 not). | E24: Joan | F24: before next cockpit | G24: Open

Sheet 7. Risk Register
A1: STRATEGIC RISK REGISTER — Q3 2026
A2: Forward-looking executive risks · what could stop a north star before it becomes a red · reviewed weekly by Joan
A3: SEVERITY auto-rates from Likelihood × Impact (3×3 matrix): H×H = Critical · H×M = High · M×M / H×L = Medium · rest = Low. The Decision Log handles reds after they surface; this looks ahead.
A4: Risk ID | B4: Risk / description | C4: North Star | D4: Likelihood | E4: Impact | F4: Severity | G4: Owner | H4: Mitigation / next action | I4: Status | J4: Last reviewed
A5: R1 | B5: Capital raise / Series A slips or is mis-sized for stage; funders move slowly | C5: Partnerships | D5: Medium | E5: High | F5: =IF(OR(D5="",E5=""),"",IF((IF(D5="High",3,IF(D5="Medium",2,1)))*(IF(E5="High",3,IF(E5="Medium",2,1)))=9,"Critical",IF((IF(D5="High",3,IF(D5="Medium",2,1)))*(IF(E5="High",3,IF(E5="Medium",2,1)))=6,"High",IF((IF(D5="High",3,IF(D5="Medium",2,1)))*(IF(E5="High",3,IF(E5="Medium",2,1)))>=3,"Medium","Low")))) -> High | G5: Dennis | H5: Sequence concessional / anchor funder first; keep named conversations warm with a next step each | I5: Monitoring
A6: R2 | B6: Revenue conversion: $11K signed of the $100K floor at wk 8/13, no new close in W8. Floor unreachable on current pace; Prisons is advocacy-paced, Rockefeller ($150k) unconverted. | C6: Revenue | D6: Medium | E6: High | F6: =IF(OR(D6="",E6=""),"",IF((IF(D6="High",3,IF(D6="Medium",2,1)))*(IF(E6="High",3,IF(E6="Medium",2,1)))=9,"Critical",IF((IF(D6="High",3,IF(D6="Medium",2,1)))*(IF(E6="High",3,IF(E6="Medium",2,1)))=6,"High",IF((IF(D6="High",3,IF(D6="Medium",2,1)))*(IF(E6="High",3,IF(E6="Medium",2,1)))>=3,"Medium","Low")))) -> High | G6: Elizabeth / Wilson | H6: State burn/runway from the restated FY26 financials, then take the floor decision with Dennis — flex it or name the deal that closes it. | I6: Open | J6: W8
A7: R3 | B7: Prisons: RESUMED as procurement advocacy (not dead). Strategically stronger (technology-neutral reframe) but near-term revenue timing now uncertain — depends on procurement reform then bid. | C7: Programmes | D7: Medium | E7: High | F7: =IF(OR(D7="",E7=""),"",IF((IF(D7="High",3,IF(D7="Medium",2,1)))*(IF(E7="High",3,IF(E7="Medium",2,1)))=9,"Critical",IF((IF(D7="High",3,IF(D7="Medium",2,1)))*(IF(E7="High",3,IF(E7="Medium",2,1)))=6,"High",IF((IF(D7="High",3,IF(D7="Medium",2,1)))*(IF(E7="High",3,IF(E7="Medium",2,1)))>=3,"Medium","Low")))) -> High | G7: Wilson | H7: Prepare detailed follow-up pack; put a lower-CAPEX LPG option in front of the Secretariat before they decide | I7: Monitoring
A8: R4 | B8: CCIQ launch timing depends on an external event that was POSTPONED — launch moved with it (not a failure or reporting gap). Platform work ongoing; documents being uploaded/reviewed. | C8: Programmes | D8: Low | E8: Medium | F8: =IF(OR(D8="",E8=""),"",IF((IF(D8="High",3,IF(D8="Medium",2,1)))*(IF(E8="High",3,IF(E8="Medium",2,1)))=9,"Critical",IF((IF(D8="High",3,IF(D8="Medium",2,1)))*(IF(E8="High",3,IF(E8="Medium",2,1)))=6,"High",IF((IF(D8="High",3,IF(D8="Medium",2,1)))*(IF(E8="High",3,IF(E8="Medium",2,1)))>=3,"Medium","Low")))) -> Low | G8: Brian | H8: Set a new launch date once the event reschedules; keep platform readiness current | I8: Monitoring
A9: R5 | B9: Unresolved partner date conflicts (RF concept note, GEAPP proposal) risk missed submission windows | C9: Partnerships | D9: Medium | E9: Medium | F9: =IF(OR(D9="",E9=""),"",IF((IF(D9="High",3,IF(D9="Medium",2,1)))*(IF(E9="High",3,IF(E9="Medium",2,1)))=9,"Critical",IF((IF(D9="High",3,IF(D9="Medium",2,1)))*(IF(E9="High",3,IF(E9="Medium",2,1)))=6,"High",IF((IF(D9="High",3,IF(D9="Medium",2,1)))*(IF(E9="High",3,IF(E9="Medium",2,1)))>=3,"Medium","Low")))) -> Medium | G9: Elizabeth / Joan | H9: Settle both dates at the week-1 cockpit (logged in Decision Log) | I9: Open
A10: R6 | B10: Concentration through Dennis (MD) + reporting discipline. REGRESSED W8: 3 of 5 did not report, including the MD; the FSD answer sits with him alone. Elizabeth 2 weeks out. | C10: Team | D10: Medium | E10: Medium | F10: =IF(OR(D10="",E10=""),"",IF((IF(D10="High",3,IF(D10="Medium",2,1)))*(IF(E10="High",3,IF(E10="Medium",2,1)))=9,"Critical",IF((IF(D10="High",3,IF(D10="Medium",2,1)))*(IF(E10="High",3,IF(E10="Medium",2,1)))=6,"High",IF((IF(D10="High",3,IF(D10="Medium",2,1)))*(IF(E10="High",3,IF(E10="Medium",2,1)))>=3,"Medium","Low")))) -> Medium | G10: Joan | H10: Reset the five-line expectation with each non-reporter before the next cockpit; keep decision rights delegated. | I10: Open | J10: W8
A11: R7 | B11: DMRV not contracted and the 31 Aug target is at risk: 4RDigital platform decision DEFERRED (18 Aug) pending hardware manufacturing. GSM remote control outstanding. | C11: Programmes | D11: Medium | E11: Medium | F11: =IF(OR(D11="",E11=""),"",IF((IF(D11="High",3,IF(D11="Medium",2,1)))*(IF(E11="High",3,IF(E11="Medium",2,1)))=9,"Critical",IF((IF(D11="High",3,IF(D11="Medium",2,1)))*(IF(E11="High",3,IF(E11="Medium",2,1)))=6,"High",IF((IF(D11="High",3,IF(D11="Medium",2,1)))*(IF(E11="High",3,IF(E11="Medium",2,1)))>=3,"Medium","Low")))) -> Medium | G11: Wilson / Brian | H11: Re-date the DMRV target, or name a provider path that does not wait on hardware. | I11: Open | J11: W8
A12: R8 | B12: UNDP and Sierra Leone revenue amounts unquantified — weakens the forecast against the floor | C12: Revenue | D12: Medium | E12: Low | F12: =IF(OR(D12="",E12=""),"",IF((IF(D12="High",3,IF(D12="Medium",2,1)))*(IF(E12="High",3,IF(E12="Medium",2,1)))=9,"Critical",IF((IF(D12="High",3,IF(D12="Medium",2,1)))*(IF(E12="High",3,IF(E12="Medium",2,1)))=6,"High",IF((IF(D12="High",3,IF(D12="Medium",2,1)))*(IF(E12="High",3,IF(E12="Medium",2,1)))>=3,"Medium","Low")))) -> Low | G12: Elizabeth / Dennis | H12: Confirm figures (logged in Decision Log); update the Revenue tracker | I12: Open
A13: R9 | B13: FSD MoU: signature targeted 17–18 Aug, NOT confirmed. Tracked-changes version with FSD (Robert Akunga) since 15 Aug. Unconfirmed is not failed, but the date passed in silence. | C13: Partnerships | D13: Medium | E13: High | F13: =IF(OR(D13="",E13=""),"",IF((IF(D13="High",3,IF(D13="Medium",2,1)))*(IF(E13="High",3,IF(E13="Medium",2,1)))=9,"Critical",IF((IF(D13="High",3,IF(D13="Medium",2,1)))*(IF(E13="High",3,IF(E13="Medium",2,1)))=6,"High",IF((IF(D13="High",3,IF(D13="Medium",2,1)))*(IF(E13="High",3,IF(E13="Medium",2,1)))>=3,"Medium","Low")))) -> High | G13: Dennis / Wilson | H13: Yes or no from Dennis before the next cockpit; if unsigned, secure a dated commitment from FSD. | I13: Open | J13: W8
A14: R10 | B14: Tectona data collection: Mui County MoU still delayed, fieldwork rerouted to other counties. Risk to county coverage and the CCIQ baseline. 5 coordinates flagged. | C14: Programmes | D14: Medium | E14: Low | F14: =IF(OR(D14="",E14=""),"",IF((IF(D14="High",3,IF(D14="Medium",2,1)))*(IF(E14="High",3,IF(E14="Medium",2,1)))=9,"Critical",IF((IF(D14="High",3,IF(D14="Medium",2,1)))*(IF(E14="High",3,IF(E14="Medium",2,1)))=6,"High",IF((IF(D14="High",3,IF(D14="Medium",2,1)))*(IF(E14="High",3,IF(E14="Medium",2,1)))>=3,"Medium","Low")))) -> Low | G14: Elizabeth / Wilson | H14: Confirm KOBO uploaded + tested before ToT; verify the 5 coordinates; set a decision date on Mui. | I14: Open | J14: W8
A15: R11 | F15: =IF(OR(D15="",E15=""),"",IF((IF(D15="High",3,IF(D15="Medium",2,1)))*(IF(E15="High",3,IF(E15="Medium",2,1)))=9,"Critical",IF((IF(D15="High",3,IF(D15="Medium",2,1)))*(IF(E15="High",3,IF(E15="Medium",2,1)))=6,"High",IF((IF(D15="High",3,IF(D15="Medium",2,1)))*(IF(E15="High",3,IF(E15="Medium",2,1)))>=3,"Medium","Low"))))
A16: R12 | F16: =IF(OR(D16="",E16=""),"",IF((IF(D16="High",3,IF(D16="Medium",2,1)))*(IF(E16="High",3,IF(E16="Medium",2,1)))=9,"Critical",IF((IF(D16="High",3,IF(D16="Medium",2,1)))*(IF(E16="High",3,IF(E16="Medium",2,1)))=6,"High",IF((IF(D16="High",3,IF(D16="Medium",2,1)))*(IF(E16="High",3,IF(E16="Medium",2,1)))>=3,"Medium","Low"))))
A17: R13 | F17: =IF(OR(D17="",E17=""),"",IF((IF(D17="High",3,IF(D17="Medium",2,1)))*(IF(E17="High",3,IF(E17="Medium",2,1)))=9,"Critical",IF((IF(D17="High",3,IF(D17="Medium",2,1)))*(IF(E17="High",3,IF(E17="Medium",2,1)))=6,"High",IF((IF(D17="High",3,IF(D17="Medium",2,1)))*(IF(E17="High",3,IF(E17="Medium",2,1)))>=3,"Medium","Low"))))
A18: R14 | F18: =IF(OR(D18="",E18=""),"",IF((IF(D18="High",3,IF(D18="Medium",2,1)))*(IF(E18="High",3,IF(E18="Medium",2,1)))=9,"Critical",IF((IF(D18="High",3,IF(D18="Medium",2,1)))*(IF(E18="High",3,IF(E18="Medium",2,1)))=6,"High",IF((IF(D18="High",3,IF(D18="Medium",2,1)))*(IF(E18="High",3,IF(E18="Medium",2,1)))>=3,"Medium","Low"))))
